microtvm_device/__init__.py
microtvm_device/device_client.py
microtvm_device/device_server.py
microtvm_device/device_utils.py
microtvm_device/microDevice_pb2.py
microtvm_device/microDevice_pb2_grpc.py
microtvm_device-0.4.0.dist-info/LICENSE
microtvm_device-0.4.0.dist-info/WHEEL
microtvm_device-0.4.0.dist-info/METADATA
microtvm_device-0.4.0.dist-info/RECORD
