Metadata-Version: 2.1
Name: microtvm-device
Version: 0.4.0
Summary: 
Home-page: https://github.com/mehrdadh/microtvm-device
License: Apache
Keywords: microTVM,tvm,device
Author: mehrdadh
Author-email: mehrdad.hessar@gmail.com
Requires-Python: >=3.7
Classifier: License :: Other/Proprietary License
Classifier: Programming Language :: Python :: 3
Classifier: Programming Language :: Python :: 3.10
Classifier: Programming Language :: Python :: 3.7
Classifier: Programming Language :: Python :: 3.8
Classifier: Programming Language :: Python :: 3.9
Requires-Dist: grpcio (>=1.39.0,<2.0.0)
Requires-Dist: grpcio-tools (>=1.39.0,<2.0.0)
Requires-Dist: pytest (>=6.2.4,<7.0.0)
Requires-Dist: tabulate (>=0.8.9,<0.9.0)
Project-URL: Repository, https://github.com/mehrdadh/microtvm-device
